xlea/__init__.py
xlea/exc.py
xlea/core/__init__.py
xlea/core/bound_schema.py
xlea/core/column.py
xlea/core/constants.py
xlea/core/reader.py
xlea/core/row.py
xlea/core/schema.py
xlea/core/types.py
xlea/providers/__init__.py
xlea/providers/openpyxl.py
xlea/providers/proto.py
xlea/providers/providers.py
xlea/providers/pyxlsb.py
xlea/providers/xlrd.py
xlea-1.0.0.dist-info/METADATA
xlea-1.0.0.dist-info/WHEEL
xlea-1.0.0.dist-info/RECORD
