Metadata-Version: 2.4
Name: xlea
Version: 1.0.0
Summary: python library that makes it easy to convert Excel tables into ORM-like objects
Author-email: ArtemDorozhkin <artanador@tutamail.com>
Requires-Python: >=3.9
Requires-Dist: openpyxl>=3.1.5
Requires-Dist: pyxlsb>=1.0.10
Requires-Dist: xlrd>=2.0.2
